{"resourceType":"Condition","id":"fee53927-c2f6-4910-8ba0-567be0f92b6c","clinicalStatus":"resolved","verificationStatus":"confirmed","code":{"coding":[{"system":"http://snomed.info/sct","code":"195662009","display":"Acute viral pharyngitis (disorder)"}],"text":"Acute viral pharyngitis (disorder)"},"subject":{"reference":"Patient/0ee8938d-bf98-47d7-b1b2-3d4d072cb086"},"context":{"reference":"Encounter/e2d3b07f-8d50-4abd-88ef-850856f4e474"},"onsetDateTime":"2009-02-18T13:11:12+00:00","abatementDateTime":"2009-02-27T13:11:12+00:00","assertedDate":"2009-02-18T13:11:12+00:00"}
