{"resourceType":"Condition","id":"5edf1ac1-b71c-4257-bef0-5451dcdf44df","clinicalStatus":"resolved","verificationStatus":"confirmed","code":{"coding":[{"system":"http://snomed.info/sct","code":"444814009","display":"Viral sinusitis (disorder)"}],"text":"Viral sinusitis (disorder)"},"subject":{"reference":"Patient/ed1b9b07-be04-4d88-b00d-b8447ba1b7a7"},"context":{"reference":"Encounter/fce0b007-c9ee-404c-870c-30c865ab7fc1"},"onsetDateTime":"1945-08-25T10:14:22+00:00","abatementDateTime":"1945-09-08T10:14:22+00:00","assertedDate":"1945-08-25T10:14:22+00:00"}
