{"resourceType": "DiagnosticReport", "id": "79136be9-c577-4504-98a3-7c169491f819", "status": "final", "code.coding.system": "http://loinc.org", "code.coding.code": "69409-1", "code.coding.display": "U.S. standard certificate of death - 2003 revision", "code.text": "U.S. standard certificate of death - 2003 revision", "idPatient": "ddf5ae5c-5646-4a76-9efd-f7e697f3b728", "subject.reference": "Patient/ddf5ae5c-5646-4a76-9efd-f7e697f3b728", "context.reference": "Encounter/9a91ccb0-b1b8-4f4a-a021-2d6e29ba485c", "effectiveDateTime": "2014-10-18T16:33:20+00:00", "issued": "2014-10-18T16:33:20.246+00:00", "result.reference": "Observation/7a7ec82c-9cf8-4ab3-b510-d9dded07b0bc", "result.display": "Cause of Death [US Standard Certificate of Death]"}