{"resourceType":"Procedure","id":"e0b4695e-041d-4353-a303-42017586d9b5","status":"completed","code":{"coding":[{"system":"http://snomed.info/sct","code":"225158009","display":"Auscultation of the fetal heart"}],"text":"Auscultation of the fetal heart"},"subject":{"reference":"Patient/94bef038-b168-47ec-bb0e-0184ae8fd604"},"context":{"reference":"Encounter/ff04d15d-a998-41f5-a4fd-f984c87f3309"},"performedPeriod":{"start":"2002-06-29T16:06:16+00:00","end":"2002-06-29T16:21:16+00:00"},"reasonReference":[{"reference":"Condition/a51b78f4-5b06-403e-b0cb-25dda6d22ed6","display":"Normal pregnancy"}]}
