{"resourceType":"Procedure","id":"8fe0c29e-c6f6-4838-8691-9fa6b6a81ca4","status":"completed","code":{"coding":[{"system":"http://snomed.info/sct","code":"428191000124101","display":"Documentation of current medications"}],"text":"Documentation of current medications"},"subject":{"reference":"Patient/2295fbd8-8572-4490-a607-61fb6c7e87e0"},"context":{"reference":"Encounter/0fe12792-b2f6-4468-a89b-a416e637c081"},"performedPeriod":{"start":"2012-11-18T14:29:45+00:00","end":"2012-11-18T14:44:45+00:00"}}
