{"resourceType":"Procedure","id":"da268d3e-01ea-4dcf-9990-7f3a0d991dee","status":"completed","code":{"coding":[{"system":"http://snomed.info/sct","code":"428191000124101","display":"Documentation of current medications"}],"text":"Documentation of current medications"},"subject":{"reference":"Patient/56f18382-87e9-423b-8908-2a83cdddf9b3"},"context":{"reference":"Encounter/112f86c2-c356-4d8a-b869-358158528743"},"performedPeriod":{"start":"2017-01-13T19:33:37+00:00","end":"2017-01-13T19:48:37+00:00"}}
