{"resourceType":"Procedure","id":"3611160d-6e8c-4cfc-8b36-7ab9d4d8c65b","status":"completed","code":{"coding":[{"system":"http://snomed.info/sct","code":"428191000124101","display":"Documentation of current medications"}],"text":"Documentation of current medications"},"subject":{"reference":"Patient/a8ab1fd7-9c21-4902-94e5-486b690b5797"},"context":{"reference":"Encounter/4b8df44f-af99-45e8-91a3-48353d703fe6"},"performedPeriod":{"start":"2017-01-21T08:34:16+00:00","end":"2017-01-21T08:49:16+00:00"}}
