{"resourceType":"Procedure","id":"f65b72d3-bbbf-487f-936c-b36de13bd117","status":"completed","code":{"coding":[{"system":"http://snomed.info/sct","code":"275833003","display":"Alpha-fetoprotein test"}],"text":"Alpha-fetoprotein test"},"subject":{"reference":"Patient/0fbd8ed9-f4c0-442d-9cfb-98879a8be0eb"},"context":{"reference":"Encounter/2008d348-286d-4965-81e5-35fd342bc5b3"},"performedPeriod":{"start":"1984-09-19T05:16:12+00:00","end":"1984-09-19T05:31:12+00:00"},"reasonReference":[{"reference":"Condition/34e52689-422a-4e53-8a1f-efc43fd0a884","display":"Normal pregnancy"}]}
